README.rst
lenum.py
setup.cfg
setup.py
labeled_enum.egg-info/PKG-INFO
labeled_enum.egg-info/SOURCES.txt
labeled_enum.egg-info/dependency_links.txt
labeled_enum.egg-info/top_level.txt