Metadata-Version: 1.1
Name: labeled-enum
Version: 1.3.1
Summary: Django friendly, iterable Enum type with labels.
Home-page: UNKNOWN
Author: Curtis Maloney
Author-email: curtis@tinbrain.net
License: UNKNOWN
Platform: UNKNOWN
Classifier: Development Status :: 5 - Production/Stable
Classifier: Intended Audience :: Developers
